Workbook

Sheet Assumptions
A1: Trinity No-Show Program — Assumptions
A2: Blue = input from analysis. Yellow = business lever the board can change.
A4: FINDINGS FROM THE ANALYSIS
A5: No-shows per year | B5: 4226 | C5: drivers.py: count / years
A6: No-show rate | B6: 0.1395 | C6: drivers.py
A7: High-risk slots per year (>30d lead) | B7: 1340 | C7: drivers.py: lead-time cohort
A8: High-risk no-show rate | B8: 0.2313 | C8: drivers.py: ~2x baseline
A9: Absorbable demand per week (rebalance) | B9: 27 | C9: capacity.py: overbooked->idle
A10: Reminder effect (adjusted, pts) | B10: 0.7 | C10: drivers.py: AFTER de-confounding
A12: BUSINESS LEVERS (board can change)
A13: Contribution per attended visit ($) | B13: 150 | C13: From Finance — key driver
A14: Reminder system cost / year ($) | B14: 45000 | C14: Vendor estimate
A15: Overbooking program cost / year ($) | B15: 20000 | C15: Staff time + scheduling
A16: Rebalancing cost / year ($) | B16: 15000 | C16: Change management
A17: Collision cost per event ($) | B17: 40 | C17: Patient-wait cost when both show
A18: Operating weeks per year | B18: 48

Sheet Cost of Problem
A1: What no-shows cost Trinity per year
A3: No-shows per year | B3: =Assumptions!B5 -> 4226
A4: Contribution lost per no-show | B4: =Assumptions!B13 -> 150
A5: Annual cost of no-shows | B5: =B3*B4 -> 633900
A7: This is the number the board asked for: a defensible figure,
A8: computed from a no-show count that reconciles to the schedule
A9: and billing, times a contribution value Finance can adjust above.

Sheet Interventions
A1: Intervention portfolio — ranked by ROI
A3: Intervention | B3: Annual benefit | C3: Annual cost | D3: Net benefit | E3: ROI | F3: Rank | G3: Fund?
A4: 1. Rebalance overbooked→idle providers | B4: =Assumptions!B9*Assumptions!B18*Assumptions!B13 -> 194400 | C4: =Assumptions!B16 -> 15000 | D4: =B4-C4 -> 179400 | E4: =IFERROR(D4/C4,0) -> 11.96
A5: 2. Controlled overbooking (high-risk) | B5: ='Overbook Downside'!B14 -> 5288.98 | C5: =Assumptions!B15 -> 20000 | D5: =B5-C5 -> -14711.02 | E5: =IFERROR(D5/C5,0) -> -0.735551
A6: 3. Structured reminders (pilot first) | B6: =(Assumptions!B5/0.1395)*(Assumptions!B10/100)*Assumptions!B13 -> 31808.602 | C6: =Assumptions!B14 -> 45000 | D6: =B6-C6 -> -13191.398 | E6: =IFERROR(D6/C6,0) -> -0.29314217
A8: PORTFOLIO TOTAL | B8: =SUM(B4:B6) -> 231497.58 | C8: =SUM(C4:C6) -> 80000 | D8: =SUM(D4:D6) -> 151497.58
A10: Budget ceiling (year one) | B10: 600000
A11: Total program cost | B11: =C8 -> 80000
A12: Under budget? | B12: =IF(B11<=B10,"YES — fits","NO — over ceiling") -> YES — fits
A14: Ranking note: reminders use the ADJUSTED effect (0.7 pts), not the
A15: naive 2.3 pts. The naive figure was ~70% selection bias. We fund
A16: reminders as a measured pilot, not on the confounded comparison.

Sheet Overbook Downside
A1: Overbooking — the downside, priced honestly
A3: The objection: overbook a slot, both patients show, someone waits.
A4: This tab prices that collision and nets it against the upside.
A6: High-risk slots overbooked / year | B6: =Assumptions!B7 -> 1340
A7: No-show rate on those slots | B7: =Assumptions!B8 -> 0.2313
A8: Recovery per slot when original no-shows | B8: =B7*Assumptions!B13 -> 34.695
A9: Collision prob. (original DOES show) | B9: =1-B7 -> 0.7687
A10: Collision cost per slot | B10: =B9*Assumptions!B17 -> 30.748
A11: Net benefit per overbooked slot | B11: =B8-B10 -> 3.947
A12: Annual collision cost (all slots) | B12: =B6*B10 -> 41202.32
A14: NET annual benefit of overbooking | B14: =B6*B11 -> 5288.98
A16: Note how THIN this is: the collision cost eats most of the
A17: recovery. Overbooking is only marginally profitable, which is
A18: why it is applied ONLY to high-risk slots and monitored. This
A19: model supports Dr. Raghavan's caution rather than dismissing it.
